LICENSE
MANIFEST.in
README.md
README.rst
setup.cfg
setup.py
xutil/__init__.py
xutil/alias.sh
xutil/aws.py
xutil/cli.py
xutil/diskio.py
xutil/helpers.py
xutil/network.py
xutil/parallelism.py
xutil/web.py
xutil.egg-info/PKG-INFO
xutil.egg-info/SOURCES.txt
xutil.egg-info/dependency_links.txt
xutil.egg-info/entry_points.txt
xutil.egg-info/requires.txt
xutil.egg-info/top_level.txt
xutil/database/README.md
xutil/database/__init__.py
xutil/database/base.py
xutil/database/base_old.py
xutil/database/etl.py
xutil/database/hive.py
xutil/database/jdbc.py
xutil/database/mongo.py
xutil/database/oracle.py
xutil/database/postgresql.py
xutil/database/redis.py
xutil/database/spark.py
xutil/database/sqlite.py
xutil/database/sqlserver.py
xutil/database/__pycache__/__init__.cpython-36.pyc
xutil/database/__pycache__/base.cpython-36.pyc
xutil/database/__pycache__/base2.cpython-36.pyc
xutil/database/__pycache__/etl.cpython-36.pyc
xutil/database/__pycache__/hive.cpython-36.pyc
xutil/database/__pycache__/jdbc.cpython-36.pyc
xutil/database/__pycache__/oracle.cpython-36.pyc
xutil/database/__pycache__/postgresql.cpython-36.pyc
xutil/database/__pycache__/spark.cpython-36.pyc
xutil/database/__pycache__/sqlite.cpython-36.pyc
xutil/database/__pycache__/sqlserver.cpython-36.pyc
xutil/database/jars/jtds-1.3.1.jar
xutil/database/jars/mysql-connector-java-6.0.6.jar
xutil/database/jars/ojdbc6-11.2.0.3.jar
xutil/database/jars/postgresql-9.4.1207.jre7.jar
xutil/database/jars/sqlite-jdbc-3.23.1.jar
xutil/database/jars/sqljdbc4-4.0.jar
xutil/database/templates/base.yaml
xutil/database/templates/hive.yaml
xutil/database/templates/oracle.yaml
xutil/database/templates/postgresql.yaml
xutil/database/templates/profile.def.yaml
xutil/database/templates/profile.yaml
xutil/database/templates/redshift.yaml
xutil/database/templates/spark.yaml
xutil/database/templates/sqlite.yaml
xutil/database/templates/sqlserver.yaml