Metadata-Version: 2.1
Name: xutil
Version: 0.2.3
Summary: Extra Useful Utilities.
Home-page: https://github.com/flarco/xutil
Author: Fritz Larco
Author-email: flarco@live.com
License: UNKNOWN
Download-URL: https://github.com/flarco/xutil/archive/master.zip
Keywords: xutil
Platform: UNKNOWN
Classifier: Programming Language :: Python :: 3
Classifier: Intended Audience :: Developers
Classifier: Intended Audience :: Education
Classifier: Intended Audience :: Science/Research
Classifier: Operating System :: MacOS
Classifier: Operating System :: Unix
Classifier: Topic :: Utilities
Provides-Extra: web
Provides-Extra: jdbc
Provides-Extra: hive
Provides-Extra: full
